<?xml version="1.0" encoding="UTF-8"?>
<!DOCTYPE JobConfiguration PUBLIC "" "JobConfig.dtd"[

<!ENTITY PROOFdir "/nfs/dust/cms/user/reimersa/.proof2">      
<!ENTITY NEVT "-1">
<!ENTITY CACHEABLE "False">
<!ENTITY OUTdir   "/nfs/dust/cms/user/reimersa/JEC/JEC_80X_v2/ClosureTest/Spring16_v8/AK4Puppi">





<!ENTITY QCDPt15to7000_pythia8_AK4Puppi SYSTEM "/nfs/dust/cms/user/reimersa/CMSSW_8_0_20/src/UHH2/common/datasets/RunII_80X_v2/MC_QCD_Pt-15to7000_Flat_pythia8.xml">
<!ENTITY QCDPt15to7000_herwigpp_AK4Puppi SYSTEM "/nfs/dust/cms/user/reimersa/CMSSW_8_0_20/src/UHH2/common/datasets/RunII_80X_v2/MC_QCD_Pt-15to7000_Flat_herwigpp.xml">
<!ENTITY QCDHt500to700_madgraph_pythia8_AK4Puppi SYSTEM "/nfs/dust/cms/user/reimersa/CMSSW_8_0_20/src/UHH2/common/datasets/RunII_80X_v2/MC_QCD_HT500to700.xml.xml">
<!ENTITY QCDHt700to1000_madgraph_pythia8_AK4Puppi SYSTEM "/nfs/dust/cms/user/reimersa/CMSSW_8_0_20/src/UHH2/common/datasets/RunII_80X_v2/MC_QCD_HT700to1000.xml.xml">
<!ENTITY QCDHt1500to2000_madgraph_pythia8_AK4Puppi SYSTEM "/nfs/dust/cms/user/reimersa/CMSSW_8_0_20/src/UHH2/common/datasets/RunII_80X_v2/MC_QCD_HT1500to2000.xml.xml">
<!ENTITY QCDHt2000toInf_madgraph_pythia8_AK4Puppi SYSTEM "/nfs/dust/cms/user/reimersa/CMSSW_8_0_20/src/UHH2/common/datasets/RunII_80X_v2/MC_QCD_HT2000toInf.xml.xml">
<!--<!ENTITY DATA_RunB_AK4Puppi SYSTEM "/nfs/dust/cms/user/reimersa/CMSSW_8_0_20/src/UHH2/common/datasets/RunII_80X_v2/">
<!ENTITY DATA_RunC_AK4Puppi SYSTEM "/nfs/dust/cms/user/reimersa/CMSSW_8_0_20/src/UHH2/common/datasets/RunII_80X_v2/">
<!ENTITY DATA_RunD_AK4Puppi SYSTEM "/nfs/dust/cms/user/reimersa/CMSSW_8_0_20/src/UHH2/common/datasets/RunII_80X_v2/">
<!ENTITY DATA_RunE_AK4Puppi SYSTEM "/nfs/dust/cms/user/reimersa/CMSSW_8_0_20/src/UHH2/common/datasets/RunII_80X_v2/">
<!ENTITY DATA_RunF_AK4Puppi SYSTEM "/nfs/dust/cms/user/reimersa/CMSSW_8_0_20/src/UHH2/common/datasets/RunII_80X_v2/">-->
<!ENTITY DATA_RunG_AK4Puppi SYSTEM "/nfs/dust/cms/user/reimersa/CMSSW_8_0_20/src/UHH2/common/datasets/RunII_80X_v2/DATA_JetHT_RunG.xml">



]>


<!--
<ConfigParse NEventsBreak="0" FileSplit="8" AutoResubmit="5"/>
<ConfigSGE RAM ="4" DISK ="3" Mail="arne.reimers@desy.de" Notification="as" Workdir="workdir_AK4Puppi_v2"/>
-->

<!-- OutputLevel controls which messages are printed; set to VERBOSE or DEBUG for more verbosity, to WARNING or ERROR for less -->
<JobConfiguration JobName="ExampleCycleJob" OutputLevel="INFO">
    <Library Name="libSUHH2BaconJets"/>
    <Package Name="SUHH2BaconJets.par" />

<Cycle Name="uhh2::AnalysisModuleRunner" OutputDirectory="&OUTdir;/" PostFix="" TargetLumi="12900" >
<!--<Cycle Name="uhh2::AnalysisModuleRunner" OutputDirectory="&OUTdir;/" PostFix="" TargetLumi="2600" RunMode="PROOF" ProofServer="lite://" ProofWorkDir="&PROOFdir;/" ProofNodes="18">-->
 


     <InputData Lumi="12900" NEventsMax="&NEVT;" Type="MC" Version="QCDPt15to7000_pythia8_AK4Puppi" Cacheable="&CACHEABLE;">
          &QCDPt15to7000_pythia8_AK4Puppi;
          <InputTree Name="AnalysisTree"/>
          <OutputTree Name="AnalysisTree"/>
     </InputData>


     <InputData Lumi="12900" NEventsMax="&NEVT;" Type="MC" Version="QCDPt15to7000_herwigpp_AK4Puppi" Cacheable="&CACHEABLE;">
          &QCDPt15to7000_herwigpp_AK4Puppi;
          <InputTree Name="AnalysisTree"/>
          <OutputTree Name="AnalysisTree"/>
     </InputData>

 
<!--	
  <InputData Lumi="12900" NEventsMax="&NEVT;" Type="DATA" Version="DATA_RunB_AK4Puppi" Cacheable="&CACHEABLE;">
       &DATA_RunB_AK4Puppi;
       <InputTree Name="AnalysisTree"/>
       <OutputTree Name="AnalysisTree"/>
  </InputData> 



  <InputData Lumi="12900" NEventsMax="&NEVT;" Type="DATA" Version="DATA_RunC_AK4Puppi" Cacheable="&CACHEABLE;">
       &DATA_RunC_AK4Puppi;
       <InputTree Name="AnalysisTree"/>
       <OutputTree Name="AnalysisTree"/>
  </InputData>



  <InputData Lumi="12900" NEventsMax="&NEVT;" Type="DATA" Version="DATA_RunD_AK4Puppi" Cacheable="&CACHEABLE;">
       &DATA_RunD_AK4Puppi;
       <InputTree Name="AnalysisTree"/>
       <OutputTree Name="AnalysisTree"/>
  </InputData>

	
  <InputData Lumi="12900" NEventsMax="&NEVT;" Type="DATA" Version="DATA_RunE_AK4Puppi" Cacheable="&CACHEABLE;">
       &DATA_RunE_AK4Puppi;
       <InputTree Name="AnalysisTree"/>
       <OutputTree Name="AnalysisTree"/>
  </InputData> 

  <InputData Lumi="12900" NEventsMax="&NEVT;" Type="DATA" Version="DATA_RunF_AK4Puppi" Cacheable="&CACHEABLE;">
       &DATA_RunF_AK4Puppi;
       <InputTree Name="AnalysisTree"/>
       <OutputTree Name="AnalysisTree"/>
  </InputData>
-->

  <InputData Lumi="12900" NEventsMax="&NEVT;" Type="DATA" Version="DATA_RunG_AK4Puppi" Cacheable="&CACHEABLE;">
       &DATA_RunG_AK4Puppi;
       <InputTree Name="AnalysisTree"/>
       <OutputTree Name="AnalysisTree"/>
  </InputData>










    <UserConfig>
      <Item Name="PrimaryVertexCollection" Value="offlineSlimmedPrimaryVertices"/>
      <Item Name="GenParticleCollection"   Value="GenParticles"/>
      <Item Name="ElectronCollection"      Value="slimmedElectronsUSER"/>
      <Item Name="MuonCollection"          Value="slimmedMuonsUSER"/>
      <Item Name="TauCollection"           Value="slimmedTaus"/>
      <!-- AK4CHS -->
      <!--<Item Name="JetCollection"           Value="slimmedJets"/>
      <Item Name="JetLabel"                Value="AK4CHS"/> -->
      <!-- AK8CHS --> 
      <!--         <Item Name="JetCollection"           Value="patJetsAK8PFCHS"/>
		   <Item Name="JetLabel"                Value="AK8CHS"/> --> 
      <!-- AK4PUPPI -->
      <Item Name="JetCollection"           Value="slimmedJetsPuppi"/>
      <Item Name="JetLabel"                Value="AK4PUPPI"/> 
      <!-- AK8PUPPI -->
      <!--         <Item Name="JetCollection"           Value="patJetsAK8PFPUPPI"/>
		   <Item Name="JetLabel"                Value="AK8PUPPI"/> -->
      <Item Name="GenJetCollection"        Value="slimmedGenJets"/>
      <!--          <Item Name="METName"                 Value="slimmedMETs"/>-->
      <!--<Item Name="METName"                 Value="slMETsCHS"/>-->
      <Item Name="METName"                 Value="slimmedMETsPuppi"/>

<!--      <Item Name="lumi_file" Value="/nfs/dust/cms/user/reimersa/CMSSW_8_0_20/src/UHH2/common/data/Cert_271036-276811_13TeV_PromptReco_Collisions16_JSON.root"/>-->
      <Item Name="lumi_file" Value="/nfs/dust/cms/user/reimersa/CMSSW_8_0_20/src/UHH2/common/data/Cert_271036-280385_13TeV_PromptReco_Collisions16_JSON_NoL1T_v2.root"/>

      <!--
      	 <Item Name="pileup_directory"           Value="/afs/desy.de/user/k/karavdia/CMSSW_8_0_20/src/UHH2/BaconJets/data/PileUp/80X/PileUP_MC_pythia8_PUFlat.root"/>
	 <Item Name="pileup_directory_data" Value="/afs/desy.de/user/k/karavdia/CMSSW_8_0_20/src/UHH2/BaconJets/data/PileUp/80X/PileUP_MC_pythia8_PUFlat.root"/>
	 <Item Name="pileup_directory_data_up"   Value="/afs/desy.de/user/k/karavdia/CMSSW_8_0_20/src/UHH2/BaconJets/data/PileUp/80X/PileUP_MC_pythia8_PUFlat.root"/>
	 <Item Name="pileup_directory_data_down" Value="/afs/desy.de/user/k/karavdia/CMSSW_8_0_20/src/UHH2/BaconJets/data/PileUp/80X/PileUP_MC_pythia8_PUFlat.root"/> 
	 <Item Name="pileup_directory_data"      Value="/afs/desy.de/user/k/karavdia/CMSSW_8_0_20/src/UHH2/BaconJets/data/PileUp/80X/800pb/nPU_minBiasXsec71300.root"/>
	 <Item Name="pileup_directory_data_up"   Value="/afs/desy.de/user/k/karavdia/CMSSW_8_0_20/src/UHH2/BaconJets/data/PileUp/80X/800pb/nPU_minBiasXsec80000.root"/>
	 <Item Name="pileup_directory_data_down" Value="/afs/desy.de/user/k/karavdia/CMSSW_8_0_20/src/UHH2/BaconJets/data/PileUp/80X/800pb/nPU_minBiasXsec58000.root"/> -->


      <Item Name="lumihists_lumi_per_bin" Value="500."/>

      <Item Name="use_sframe_weight" Value="false"/>

      <Item Name="trigger40" Value="HLT_DiPFJetAve40_v*"/>
      <Item Name="trigger60" Value="HLT_DiPFJetAve60_v*"/>
      <Item Name="trigger80" Value="HLT_DiPFJetAve80_v*"/>
      <Item Name="trigger140" Value="HLT_DiPFJetAve140_v*"/>
      <Item Name="trigger200" Value="HLT_DiPFJetAve200_v*"/>
      <Item Name="trigger260" Value="HLT_DiPFJetAve260_v*"/>
      <Item Name="trigger320" Value="HLT_DiPFJetAve320_v*"/>
      <Item Name="trigger400" Value="HLT_DiPFJetAve400_v*"/>
      <Item Name="trigger500" Value="HLT_DiPFJetAve500_v*"/>
      <Item Name="trigger60_HFJEC" Value="HLT_DiPFJetAve60_HFJEC_v*"/>
      <Item Name="trigger80_HFJEC" Value="HLT_DiPFJetAve80_HFJEC_v*"/>
      <Item Name="trigger100_HFJEC" Value="HLT_DiPFJetAve100_HFJEC_v*"/>
      <Item Name="trigger160_HFJEC" Value="HLT_DiPFJetAve160_HFJEC_v*"/>
      <Item Name="trigger220_HFJEC" Value="HLT_DiPFJetAve220_HFJEC_v*"/>
      <Item Name="trigger300_HFJEC" Value="HLT_DiPFJetAve300_HFJEC_v*"/>


	<!-- Closure test? -->
	<Item Name="ClosureTest" Value="true"/>
	<!-- Systematic uncertainties -->
	<Item Name="jersmear_direction" Value="nominal"/>


            <!-- tell AnalysisModuleRunner that we use a completely user-defined event format -->
       <!--     <Item Name="userEventFormat" Value="true" /> -->
	  <!-- <Item Name="userEventFormat" Value="false" /> -->
            <!-- the class name of the AnalysisModule subclasses to run: -->
            <Item Name="AnalysisModule" Value="TestModule" /> 
	<!--    <Item Name="MCreweight" Value="false" /> -->  

        </UserConfig>
    </Cycle>
</JobConfiguration>
